ShenduXuexi500Wen/README.md
ShenduXuexi500Wen/__init__.py
ShenduXuexi500Wen/__main__.py
ShenduXuexi500Wen/file.epub
ShenduXuexi500Wen/index.html
ShenduXuexi500Wen/css/__init__.py
ShenduXuexi500Wen/css/annotations.css
ShenduXuexi500Wen/css/main.css
ShenduXuexi500Wen/css/normalize.css
ShenduXuexi500Wen/css/popup.css
ShenduXuexi500Wen/font/__init__.py
ShenduXuexi500Wen/font/fontello.eot
ShenduXuexi500Wen/font/fontello.svg
ShenduXuexi500Wen/font/fontello.ttf
ShenduXuexi500Wen/font/fontello.woff
ShenduXuexi500Wen/img/__init__.py
ShenduXuexi500Wen/img/annotator-glyph-sprite.png
ShenduXuexi500Wen/img/annotator-icon-sprite.png
ShenduXuexi500Wen/img/apple-touch-icon.png
ShenduXuexi500Wen/img/cancelfullscreen.png
ShenduXuexi500Wen/img/close.png
ShenduXuexi500Wen/img/fullscreen.png
ShenduXuexi500Wen/img/loader.gif
ShenduXuexi500Wen/img/menu-icon.png
ShenduXuexi500Wen/img/save.png
ShenduXuexi500Wen/img/saved.png
ShenduXuexi500Wen/img/settings-s.png
ShenduXuexi500Wen/img/settings.png
ShenduXuexi500Wen/img/star.png
ShenduXuexi500Wen/js/__init__.py
ShenduXuexi500Wen/js/epub.js
ShenduXuexi500Wen/js/epub.min.js
ShenduXuexi500Wen/js/epub.min.map
ShenduXuexi500Wen/js/hooks.min.js
ShenduXuexi500Wen/js/hooks.min.map
ShenduXuexi500Wen/js/reader.js
ShenduXuexi500Wen/js/reader.js.map
ShenduXuexi500Wen/js/reader.min.js
ShenduXuexi500Wen/js/reader.min.map
ShenduXuexi500Wen/js/hooks/__init__.py
ShenduXuexi500Wen/js/hooks/extensions/__init__.py
ShenduXuexi500Wen/js/hooks/extensions/highlight.js
ShenduXuexi500Wen/js/libs/__init__.py
ShenduXuexi500Wen/js/libs/jquery.min.js
ShenduXuexi500Wen/js/libs/localforage.min.js
ShenduXuexi500Wen/js/libs/screenfull.js
ShenduXuexi500Wen/js/libs/screenfull.min.js
ShenduXuexi500Wen/js/libs/zip.min.js
ShenduXuexi500Wen/js/plugins/__init__.py
ShenduXuexi500Wen/js/plugins/hypothesis.js
ShenduXuexi500Wen/js/plugins/search.js
shendu_xuexi_500_wen-2024.3.5.0.dist-info/METADATA
shendu_xuexi_500_wen-2024.3.5.0.dist-info/WHEEL
shendu_xuexi_500_wen-2024.3.5.0.dist-info/entry_points.txt
shendu_xuexi_500_wen-2024.3.5.0.dist-info/top_level.txt
shendu_xuexi_500_wen-2024.3.5.0.dist-info/RECORD
